.gitignore
README.rst
setup.py
opensrscli/__init__.py
opensrscli/parser.py
opensrscli/prefs.py
opensrscli.egg-info/PKG-INFO
opensrscli.egg-info/SOURCES.txt
opensrscli.egg-info/dependency_links.txt
opensrscli.egg-info/entry_points.txt
opensrscli.egg-info/requires.txt
opensrscli.egg-info/top_level.txt