Metadata-Version: 1.0
Name: opensrscli
Version: 0.1.7
Summary: A CLI for OpenSRS reseller accounts
Home-page: http://pypi.python.org/opensrscli
Author: Shawn Siefkas
Author-email: shawn.siefkas@meredith.com
License: BSD
Keywords: opensrs
Platform: UNKNOWN
Classifier: Development Status :: 3 - Alpha
Classifier: Topic :: Utilities
Classifier: License :: OSI Approved :: BSD License
